LICENSE
README.md
setup.py
translation_as_console_table.py
word_translator_client.py
word_translator_py.egg-info/PKG-INFO
word_translator_py.egg-info/SOURCES.txt
word_translator_py.egg-info/dependency_links.txt
word_translator_py.egg-info/top_level.txt