Metadata-Version: 2.1
Name: word-translator-py
Version: 0.1.0
Summary: A word translator using Word Reference (wordreference.com) to retrieve all the information contained in the HTML document
Author: Guillermo Rodolfo Ellison
License-File: LICENSE
